fastapi_versioning/__init__.py
fastapi_versioning/routing.py
fastapi_versioning/versioning.py
fastapi_versioning-0.10.0.dist-info/LICENSE
fastapi_versioning-0.10.0.dist-info/METADATA
fastapi_versioning-0.10.0.dist-info/WHEEL
fastapi_versioning-0.10.0.dist-info/top_level.txt
fastapi_versioning-0.10.0.dist-info/RECORD
