Metadata-Version: 2.1
Name: fastapi_versioning
Version: 0.10.0
Summary: api versioning for fastapi web applications
Home-page: https://github.com/DeanWay/fastapi-versioning
Author: Dean Way
License: UNKNOWN
Platform: UNKNOWN
Classifier: Programming Language :: Python :: 3.6
Classifier: Programming Language :: Python :: 3.7
Classifier: Programming Language :: Python :: 3.8
Classifier: License :: OSI Approved :: MIT License
Classifier: Operating System :: OS Independent
Requires-Python: >=3.6
License-File: LICENSE
